polar_api/PolarAPI.py
polar_api/__init__.py
polar_api/cleaning.py
polar_api/polar_api.py
scripts/__init__.py
scripts/download_raw_data.py
scripts/get_player_session_trimmed.py
scripts/get_session_raw_gps.py
scripts/gps_data_project.py
scripts/session_viz.py
utilities/__init__.py
utilities/metadata.py
utilities/polar_IO.py
utilities/polar_api_old.py
polar_api-2.0.0.dist-info/METADATA
polar_api-2.0.0.dist-info/WHEEL
polar_api-2.0.0.dist-info/top_level.txt
polar_api-2.0.0.dist-info/RECORD
